{
  "awayTeam": {
    "name": "Suns",
    "score": 94,
    "tricode": "PHX"
  },
  "date": "2026-02-19",
  "gameId": "0022500798",
  "homeTeam": {
    "name": "Spurs",
    "score": 121,
    "tricode": "SAS"
  },
  "periodTotals": {
    "away": [
      {
        "fg3a": 42,
        "fg3m": 12,
        "fga": 105,
        "fgm": 39,
        "fta": 6,
        "ftm": 4,
        "period": "Game",
        "pts": 94
      }
    ],
    "home": [
      {
        "fg3a": 37,
        "fg3m": 13,
        "fga": 87,
        "fgm": 45,
        "fta": 20,
        "ftm": 18,
        "period": "Game",
        "pts": 121
      }
    ]
  },
  "players": [
    {
      "name": "Devin Vassell",
      "playerId": "1630170",
      "position": "G-F",
      "starter": true,
      "stints": [
        {
          "ast": 1,
          "blk": 0,
          "fg3a": 2,
          "fg3m": 1,
          "fga": 5,
          "fgm": 3,
          "fta": 0,
          "ftm": 0,
          "inTime": "12:00",
          "minutes": 9.1,
          "oreb": 0,
          "outTime": "2:53",
          "period": 1,
          "pf": 0,
          "plusMinus": 4,
          "pts": 7,
          "reb": 2,
          "stl": 0,
          "tov": 1
        },
        {
          "ast": 1,
          "blk": 0,
          "fg3a": 2,
          "fg3m": 0,
          "fga": 2,
          "fgm": 0,
          "fta": 0,
          "ftm": 0,
          "inTime": "6:57",
          "minutes": 7.0,
          "oreb": 0,
          "outTime": "0:00",
          "period": 2,
          "pf": 0,
          "plusMinus": -2,
          "pts": 0,
          "reb": 0,
          "stl": 0,
          "tov": 0
        },
        {
          "ast": 0,
          "blk": 0,
          "fg3a": 1,
          "fg3m": 1,
          "fga": 2,
          "fgm": 2,
          "fta": 0,
          "ftm": 0,
          "inTime": "12:00",
          "minutes": 6.6,
          "oreb": 0,
          "outTime": "5:23",
          "period": 3,
          "pf": 0,
          "plusMinus": 4,
          "pts": 5,
          "reb": 0,
          "stl": 0,
          "tov": 0
        }
      ],
      "team": "SAS",
      "totals": {
        "ast": 2,
        "blk": 0,
        "eff": 11,
        "fg3a": 5,
        "fg3m": 2,
        "fga": 9,
        "fgm": 5,
        "fta": 0,
        "ftm": 0,
        "hv": 3,
        "min": 22.7,
        "oreb": 0,
        "pf": 0,
        "plusMinus": 17,
        "prod": 0.66,
        "pts": 12,
        "reb": 2,
        "stl": 0,
        "tov": 1
      }
    },
    {
      "name": "Julian Champagnie",
      "playerId": "1630577",
      "position": "F",
      "starter": true,
      "stints": [
        {
          "ast": 0,
          "blk": 0,
          "fg3a": 0,
          "fg3m": 0,
          "fga": 1,
          "fgm": 1,
          "fta": 0,
          "ftm": 0,
          "inTime": "12:00",
          "minutes": 4.7,
          "oreb": 0,
          "outTime": "7:19",
          "period": 1,
          "pf": 1,
          "plusMinus": 0,
          "pts": 2,
          "reb": 2,
          "stl": 0,
          "tov": 0
        },
        {
          "ast": 1,
          "blk": 0,
          "fg3a": 1,
          "fg3m": 0,
          "fga": 1,
          "fgm": 0,
          "fta": 0,
          "ftm": 0,
          "inTime": "2:53",
          "minutes": 2.9,
          "oreb": 0,
          "outTime": "0:00",
          "period": 1,
          "pf": 0,
          "plusMinus": 1,
          "pts": 0,
          "reb": 1,
          "stl": 0,
          "tov": 0
        },
        {
          "ast": 0,
          "blk": 0,
          "fg3a": 1,
          "fg3m": 1,
          "fga": 1,
          "fgm": 1,
          "fta": 0,
          "ftm": 0,
          "inTime": "12:00",
          "minutes": 5.0,
          "oreb": 0,
          "outTime": "6:57",
          "period": 2,
          "pf": 0,
          "plusMinus": 6,
          "pts": 3,
          "reb": 2,
          "stl": 0,
          "tov": 0
        },
        {
          "ast": 0,
          "blk": 0,
          "fg3a": 0,
          "fg3m": 0,
          "fga": 0,
          "fgm": 0,
          "fta": 0,
          "ftm": 0,
          "inTime": "12:00",
          "minutes": 5.2,
          "oreb": 0,
          "outTime": "6:50",
          "period": 3,
          "pf": 0,
          "plusMinus": 10,
          "pts": 0,
          "reb": 0,
          "stl": 0,
          "tov": 0
        },
        {
          "ast": 0,
          "blk": 0,
          "fg3a": 0,
          "fg3m": 0,
          "fga": 0,
          "fgm": 0,
          "fta": 3,
          "ftm": 3,
          "inTime": "5:23",
          "minutes": 4.6,
          "oreb": 0,
          "outTime": "0:48",
          "period": 3,
          "pf": 0,
          "plusMinus": 0,
          "pts": 3,
          "reb": 1,
          "stl": 0,
          "tov": 0
        }
      ],
      "team": "SAS",
      "totals": {
        "ast": 1,
        "blk": 0,
        "eff": 14,
        "fg3a": 2,
        "fg3m": 1,
        "fga": 3,
        "fgm": 2,
        "fta": 3,
        "ftm": 3,
        "hv": 7,
        "min": 22.4,
        "oreb": 0,
        "pf": 1,
        "plusMinus": 20,
        "prod": 0.67,
        "pts": 8,
        "reb": 6,
        "stl": 0,
        "tov": 0
      }
    },
    {
      "name": "Victor Wembanyama",
      "playerId": "1641705",
      "position": "F-C",
      "starter": true,
      "stints": [
        {
          "ast": 0,
          "blk": 2,
          "fg3a": 1,
          "fg3m": 0,
          "fga": 3,
          "fgm": 1,
          "fta": 0,
          "ftm": 0,
          "inTime": "12:00",
          "minutes": 6.0,
          "oreb": 0,
          "outTime": "6:00",
          "period": 1,
          "pf": 0,
          "plusMinus": 1,
          "pts": 2,
          "reb": 3,
          "stl": 0,
          "tov": 0
        },
        {
          "ast": 1,
          "blk": 1,
          "fg3a": 2,
          "fg3m": 0,
          "fga": 6,
          "fgm": 3,
          "fta": 0,
          "ftm": 0,
          "inTime": "12:00",
          "minutes": 7.2,
          "oreb": 0,
          "outTime": "4:46",
          "period": 2,
          "pf": 0,
          "plusMinus": 10,
          "pts": 6,
          "reb": 1,
          "stl": 0,
          "tov": 0
        },
        {
          "ast": 0,
          "blk": 0,
          "fg3a": 0,
          "fg3m": 0,
          "fga": 1,
          "fgm": 0,
          "fta": 2,
          "ftm": 2,
          "inTime": "2:35",
          "minutes": 2.6,
          "oreb": 0,
          "outTime": "0:00",
          "period": 2,
          "pf": 0,
          "plusMinus": -7,
          "pts": 2,
          "reb": 1,
          "stl": 0,
          "tov": 0
        },
        {
          "ast": 3,
          "blk": 2,
          "fg3a": 1,
          "fg3m": 1,
          "fga": 4,
          "fgm": 3,
          "fta": 0,
          "ftm": 0,
          "inTime": "12:00",
          "minutes": 6.6,
          "oreb": 0,
          "outTime": "5:23",
          "period": 3,
          "pf": 1,
          "plusMinus": 4,
          "pts": 7,
          "reb": 5,
          "stl": 1,
          "tov": 1
        },
        {
          "ast": 0,
          "blk": 0,
          "fg3a": 0,
          "fg3m": 0,
          "fga": 1,
          "fgm": 0,
          "fta": 0,
          "ftm": 0,
          "inTime": "12:00",
          "minutes": 2.3,
          "oreb": 1,
          "outTime": "9:41",
          "period": 4,
          "pf": 0,
          "plusMinus": 4,
          "pts": 0,
          "reb": 1,
          "stl": 0,
          "tov": 0
        }
      ],
      "team": "SAS",
      "totals": {
        "ast": 4,
        "blk": 5,
        "eff": 29,
        "fg3a": 4,
        "fg3m": 1,
        "fga": 15,
        "fgm": 7,
        "fta": 2,
        "ftm": 2,
        "hv": 20,
        "min": 24.8,
        "oreb": 1,
        "pf": 1,
        "plusMinus": 23,
        "prod": 1.49,
        "pts": 17,
        "reb": 11,
        "stl": 1,
        "tov": 1
      }
    },
    {
      "name": "Stephon Castle",
      "playerId": "1642264",
      "position": "G",
      "starter": true,
      "stints": [
        {
          "ast": 4,
          "blk": 0,
          "fg3a": 0,
          "fg3m": 0,
          "fga": 2,
          "fgm": 2,
          "fta": 2,
          "ftm": 2,
          "inTime": "12:00",
          "minutes": 6.6,
          "oreb": 1,
          "outTime": "5:24",
          "period": 1,
          "pf": 1,
          "plusMinus": 3,
          "pts": 6,
          "reb": 1,
          "stl": 0,
          "tov": 1
        },
        {
          "ast": 2,
          "blk": 0,
          "fg3a": 1,
          "fg3m": 1,
          "fga": 2,
          "fgm": 2,
          "fta": 0,
          "ftm": 0,
          "inTime": "10:31",
          "minutes": 3.6,
          "oreb": 1,
          "outTime": "6:57",
          "period": 2,
          "pf": 0,
          "plusMinus": 3,
          "pts": 5,
          "reb": 1,
          "stl": 1,
          "tov": 0
        },
        {
          "ast": 1,
          "blk": 0,
          "fg3a": 0,
          "fg3m": 0,
          "fga": 2,
          "fgm": 1,
          "fta": 0,
          "ftm": 0,
          "inTime": "4:46",
          "minutes": 2.2,
          "oreb": 0,
          "outTime": "2:35",
          "period": 2,
          "pf": 2,
          "plusMinus": 4,
          "pts": 2,
          "reb": 0,
          "stl": 0,
          "tov": 0
        },
        {
          "ast": 1,
          "blk": 0,
          "fg3a": 2,
          "fg3m": 1,
          "fga": 3,
          "fgm": 2,
          "fta": 0,
          "ftm": 0,
          "inTime": "12:00",
          "minutes": 4.7,
          "oreb": 0,
          "outTime": "7:19",
          "period": 3,
          "pf": 2,
          "plusMinus": 8,
          "pts": 5,
          "reb": 0,
          "stl": 0,
          "tov": 0
        },
        {
          "ast": 0,
          "blk": 0,
          "fg3a": 0,
          "fg3m": 0,
          "fga": 1,
          "fgm": 1,
          "fta": 0,
          "ftm": 0,
          "inTime": "1:48",
          "minutes": 1.8,
          "oreb": 0,
          "outTime": "0:00",
          "period": 3,
          "pf": 0,
          "plusMinus": 3,
          "pts": 2,
          "reb": 0,
          "stl": 1,
          "tov": 1
        },
        {
          "ast": 1,
          "blk": 0,
          "fg3a": 1,
          "fg3m": 0,
          "fga": 1,
          "fgm": 0,
          "fta": 0,
          "ftm": 0,
          "inTime": "12:00",
          "minutes": 2.3,
          "oreb": 0,
          "outTime": "9:41",
          "period": 4,
          "pf": 0,
          "plusMinus": 3,
          "pts": 0,
          "reb": 0,
          "stl": 1,
          "tov": 0
        }
      ],
      "team": "SAS",
      "totals": {
        "ast": 4,
        "blk": 0,
        "eff": 24,
        "fg3a": 4,
        "fg3m": 2,
        "fga": 11,
        "fgm": 8,
        "fta": 2,
        "ftm": 2,
        "hv": 7,
        "min": 21.1,
        "oreb": 1,
        "pf": 5,
        "plusMinus": 22,
        "prod": 1.28,
        "pts": 20,
        "reb": 2,
        "stl": 3,
        "tov": 2
      }
    },
    {
      "name": "De'Aaron Fox",
      "playerId": "1628368",
      "position": "G",
      "starter": true,
      "stints": [
        {
          "ast": 1,
          "blk": 0,
          "fg3a": 1,
          "fg3m": 0,
          "fga": 2,
          "fgm": 0,
          "fta": 2,
          "ftm": 2,
          "inTime": "12:00",
          "minutes": 5.0,
          "oreb": 0,
          "outTime": "7:00",
          "period": 1,
          "pf": 0,
          "plusMinus": -1,
          "pts": 2,
          "reb": 1,
          "stl": 0,
          "tov": 0
        },
        {
          "ast": 0,
          "blk": 0,
          "fg3a": 1,
          "fg3m": 0,
          "fga": 2,
          "fgm": 0,
          "fta": 2,
          "ftm": 2,
          "inTime": "2:53",
          "minutes": 2.9,
          "oreb": 0,
          "outTime": "0:00",
          "period": 1,
          "pf": 0,
          "plusMinus": 1,
          "pts": 2,
          "reb": 0,
          "stl": 0,
          "tov": 0
        },
        {
          "ast": 1,
          "blk": 0,
          "fg3a": 0,
          "fg3m": 0,
          "fga": 0,
          "fgm": 0,
          "fta": 0,
          "ftm": 0,
          "inTime": "12:00",
          "minutes": 1.5,
          "oreb": 0,
          "outTime": "10:31",
          "period": 2,
          "pf": 0,
          "plusMinus": 6,
          "pts": 0,
          "reb": 0,
          "stl": 0,
          "tov": 0
        },
        {
          "ast": 1,
          "blk": 0,
          "fg3a": 1,
          "fg3m": 0,
          "fga": 1,
          "fgm": 0,
          "fta": 2,
          "ftm": 1,
          "inTime": "3:35",
          "minutes": 3.6,
          "oreb": 0,
          "outTime": "0:00",
          "period": 2,
          "pf": 1,
          "plusMinus": -5,
          "pts": 1,
          "reb": 0,
          "stl": 0,
          "tov": 0
        },
        {
          "ast": 4,
          "blk": 0,
          "fg3a": 1,
          "fg3m": 1,
          "fga": 3,
          "fgm": 3,
          "fta": 0,
          "ftm": 0,
          "inTime": "12:00",
          "minutes": 6.6,
          "oreb": 0,
          "outTime": "5:23",
          "period": 3,
          "pf": 1,
          "plusMinus": 4,
          "pts": 7,
          "reb": 2,
          "stl": 0,
          "tov": 0
        },
        {
          "ast": 2,
          "blk": 0,
          "fg3a": 1,
          "fg3m": 1,
          "fga": 1,
          "fgm": 1,
          "fta": 0,
          "ftm": 0,
          "inTime": "12:00",
          "minutes": 2.3,
          "oreb": 0,
          "outTime": "9:41",
          "period": 4,
          "pf": 0,
          "plusMinus": 4,
          "pts": 3,
          "reb": 0,
          "stl": 0,
          "tov": 1
        }
      ],
      "team": "SAS",
      "totals": {
        "ast": 8,
        "blk": 0,
        "eff": 19,
        "fg3a": 5,
        "fg3m": 2,
        "fga": 9,
        "fgm": 4,
        "fta": 6,
        "ftm": 5,
        "hv": 10,
        "min": 21.9,
        "oreb": 0,
        "pf": 2,
        "plusMinus": 20,
        "prod": 1.14,
        "pts": 15,
        "reb": 3,
        "stl": 0,
        "tov": 1
      }
    },
    {
      "name": "Keldon Johnson",
      "playerId": "1629640",
      "position": "F-G",
      "starter": false,
      "stints": [
        {
          "ast": 0,
          "blk": 0,
          "fg3a": 2,
          "fg3m": 0,
          "fga": 3,
          "fgm": 1,
          "fta": 0,
          "ftm": 0,
          "inTime": "7:19",
          "minutes": 7.3,
          "oreb": 0,
          "outTime": "0:00",
          "period": 1,
          "pf": 1,
          "plusMinus": 5,
          "pts": 2,
          "reb": 1,
          "stl": 0,
          "tov": 1
        },
        {
          "ast": 0,
          "blk": 0,
          "fg3a": 0,
          "fg3m": 0,
          "fga": 0,
          "fgm": 0,
          "fta": 0,
          "ftm": 0,
          "inTime": "6:07",
          "minutes": 3.2,
          "oreb": 0,
          "outTime": "2:54",
          "period": 2,
          "pf": 0,
          "plusMinus": 4,
          "pts": 0,
          "reb": 0,
          "stl": 0,
          "tov": 0
        },
        {
          "ast": 1,
          "blk": 0,
          "fg3a": 0,
          "fg3m": 0,
          "fga": 3,
          "fgm": 1,
          "fta": 2,
          "ftm": 2,
          "inTime": "7:19",
          "minutes": 7.3,
          "oreb": 0,
          "outTime": "0:00",
          "period": 3,
          "pf": 0,
          "plusMinus": 6,
          "pts": 4,
          "reb": 0,
          "stl": 0,
          "tov": 0
        },
        {
          "ast": 0,
          "blk": 0,
          "fg3a": 0,
          "fg3m": 0,
          "fga": 0,
          "fgm": 0,
          "fta": 0,
          "ftm": 0,
          "inTime": "12:00",
          "minutes": 2.3,
          "oreb": 0,
          "outTime": "9:41",
          "period": 4,
          "pf": 0,
          "plusMinus": 3,
          "pts": 0,
          "reb": 1,
          "stl": 0,
          "tov": 0
        }
      ],
      "team": "SAS",
      "totals": {
        "ast": 1,
        "blk": 0,
        "eff": 4,
        "fg3a": 2,
        "fg3m": 0,
        "fga": 6,
        "fgm": 2,
        "fta": 2,
        "ftm": 2,
        "hv": 2,
        "min": 20.2,
        "oreb": 0,
        "pf": 1,
        "plusMinus": 20,
        "prod": 0.4,
        "pts": 6,
        "reb": 2,
        "stl": 0,
        "tov": 1
      }
    },
    {
      "name": "Dylan Harper",
      "playerId": "1642844",
      "position": "G",
      "starter": false,
      "stints": [
        {
          "ast": 1,
          "blk": 0,
          "fg3a": 1,
          "fg3m": 1,
          "fga": 2,
          "fgm": 2,
          "fta": 0,
          "ftm": 0,
          "inTime": "7:00",
          "minutes": 4.1,
          "oreb": 0,
          "outTime": "2:53",
          "period": 1,
          "pf": 0,
          "plusMinus": 5,
          "pts": 5,
          "reb": 0,
          "stl": 0,
          "tov": 0
        },
        {
          "ast": 0,
          "blk": 0,
          "fg3a": 0,
          "fg3m": 0,
          "fga": 1,
          "fgm": 1,
          "fta": 2,
          "ftm": 1,
          "inTime": "6:57",
          "minutes": 3.4,
          "oreb": 0,
          "outTime": "3:35",
          "period": 2,
          "pf": 0,
          "plusMinus": 3,
          "pts": 3,
          "reb": 0,
          "stl": 1,
          "tov": 0
        },
        {
          "ast": 0,
          "blk": 0,
          "fg3a": 0,
          "fg3m": 0,
          "fga": 0,
          "fgm": 0,
          "fta": 0,
          "ftm": 0,
          "inTime": "2:54",
          "minutes": 2.9,
          "oreb": 0,
          "outTime": "0:00",
          "period": 2,
          "pf": 0,
          "plusMinus": -5,
          "pts": 0,
          "reb": 0,
          "stl": 0,
          "tov": 0
        },
        {
          "ast": 1,
          "blk": 0,
          "fg3a": 1,
          "fg3m": 0,
          "fga": 3,
          "fgm": 1,
          "fta": 0,
          "ftm": 0,
          "inTime": "6:50",
          "minutes": 5.0,
          "oreb": 0,
          "outTime": "1:48",
          "period": 3,
          "pf": 0,
          "plusMinus": 5,
          "pts": 2,
          "reb": 0,
          "stl": 0,
          "tov": 1
        },
        {
          "ast": 0,
          "blk": 0,
          "fg3a": 0,
          "fg3m": 0,
          "fga": 0,
          "fgm": 0,
          "fta": 0,
          "ftm": 0,
          "inTime": "0:48",
          "minutes": 0.8,
          "oreb": 0,
          "outTime": "0:00",
          "period": 3,
          "pf": 0,
          "plusMinus": 0,
          "pts": 0,
          "reb": 1,
          "stl": 0,
          "tov": 0
        },
        {
          "ast": 0,
          "blk": 0,
          "fg3a": 3,
          "fg3m": 1,
          "fga": 5,
          "fgm": 3,
          "fta": 0,
          "ftm": 0,
          "inTime": "9:41",
          "minutes": 9.7,
          "oreb": 0,
          "outTime": "0:00",
          "period": 4,
          "pf": 0,
          "plusMinus": -4,
          "pts": 7,
          "reb": 0,
          "stl": 0,
          "tov": 2
        }
      ],
      "team": "SAS",
      "totals": {
        "ast": 1,
        "blk": 0,
        "eff": 12,
        "fg3a": 5,
        "fg3m": 2,
        "fga": 11,
        "fgm": 7,
        "fta": 2,
        "ftm": 1,
        "hv": 0,
        "min": 25.9,
        "oreb": 0,
        "pf": 0,
        "plusMinus": 4,
        "prod": 0.66,
        "pts": 17,
        "reb": 1,
        "stl": 1,
        "tov": 3
      }
    },
    {
      "name": "Luke Kornet",
      "playerId": "1628436",
      "position": "C-F",
      "starter": false,
      "stints": [
        {
          "ast": 1,
          "blk": 0,
          "fg3a": 0,
          "fg3m": 0,
          "fga": 1,
          "fgm": 1,
          "fta": 0,
          "ftm": 0,
          "inTime": "6:00",
          "minutes": 6.0,
          "oreb": 0,
          "outTime": "0:00",
          "period": 1,
          "pf": 0,
          "plusMinus": 4,
          "pts": 2,
          "reb": 4,
          "stl": 0,
          "tov": 0
        },
        {
          "ast": 0,
          "blk": 1,
          "fg3a": 0,
          "fg3m": 0,
          "fga": 3,
          "fgm": 3,
          "fta": 0,
          "ftm": 0,
          "inTime": "4:46",
          "minutes": 4.8,
          "oreb": 3,
          "outTime": "0:00",
          "period": 2,
          "pf": 0,
          "plusMinus": -3,
          "pts": 6,
          "reb": 3,
          "stl": 0,
          "tov": 0
        },
        {
          "ast": 1,
          "blk": 0,
          "fg3a": 0,
          "fg3m": 0,
          "fga": 1,
          "fgm": 1,
          "fta": 0,
          "ftm": 0,
          "inTime": "5:23",
          "minutes": 5.4,
          "oreb": 2,
          "outTime": "0:00",
          "period": 3,
          "pf": 0,
          "plusMinus": 0,
          "pts": 2,
          "reb": 2,
          "stl": 0,
          "tov": 0
        }
      ],
      "team": "SAS",
      "totals": {
        "ast": 2,
        "blk": 1,
        "eff": 22,
        "fg3a": 0,
        "fg3m": 0,
        "fga": 5,
        "fgm": 5,
        "fta": 0,
        "ftm": 0,
        "hv": 12,
        "min": 16.1,
        "oreb": 3,
        "pf": 0,
        "plusMinus": 1,
        "prod": 1.37,
        "pts": 10,
        "reb": 9,
        "stl": 0,
        "tov": 0
      }
    },
    {
      "name": "Harrison Barnes",
      "playerId": "203084",
      "position": "F",
      "starter": false,
      "stints": [
        {
          "ast": 0,
          "blk": 0,
          "fg3a": 2,
          "fg3m": 0,
          "fga": 3,
          "fgm": 0,
          "fta": 0,
          "ftm": 0,
          "inTime": "5:24",
          "minutes": 5.4,
          "oreb": 1,
          "outTime": "0:00",
          "period": 1,
          "pf": 0,
          "plusMinus": 2,
          "pts": 0,
          "reb": 1,
          "stl": 0,
          "tov": 0
        },
        {
          "ast": 3,
          "blk": 0,
          "fg3a": 1,
          "fg3m": 0,
          "fga": 3,
          "fgm": 1,
          "fta": 1,
          "ftm": 1,
          "inTime": "12:00",
          "minutes": 7.2,
          "oreb": 3,
          "outTime": "4:46",
          "period": 2,
          "pf": 0,
          "plusMinus": 6,
          "pts": 3,
          "reb": 3,
          "stl": 0,
          "tov": 0
        },
        {
          "ast": 1,
          "blk": 0,
          "fg3a": 0,
          "fg3m": 0,
          "fga": 0,
          "fgm": 0,
          "fta": 0,
          "ftm": 0,
          "inTime": "5:23",
          "minutes": 5.4,
          "oreb": 0,
          "outTime": "0:00",
          "period": 3,
          "pf": 0,
          "plusMinus": 2,
          "pts": 0,
          "reb": 0,
          "stl": 0,
          "tov": 0
        },
        {
          "ast": 1,
          "blk": 0,
          "fg3a": 1,
          "fg3m": 1,
          "fga": 2,
          "fgm": 2,
          "fta": 0,
          "ftm": 0,
          "inTime": "12:00",
          "minutes": 2.3,
          "oreb": 0,
          "outTime": "9:41",
          "period": 4,
          "pf": 0,
          "plusMinus": 3,
          "pts": 5,
          "reb": 0,
          "stl": 0,
          "tov": 0
        }
      ],
      "team": "SAS",
      "totals": {
        "ast": 4,
        "blk": 0,
        "eff": 11,
        "fg3a": 4,
        "fg3m": 1,
        "fga": 8,
        "fgm": 3,
        "fta": 1,
        "ftm": 1,
        "hv": 8,
        "min": 20.3,
        "oreb": 3,
        "pf": 0,
        "plusMinus": 16,
        "prod": 0.79,
        "pts": 8,
        "reb": 4,
        "stl": 0,
        "tov": 0
      }
    },
    {
      "name": "Carter Bryant",
      "playerId": "1642868",
      "position": "F",
      "starter": false,
      "stints": [
        {
          "ast": 1,
          "blk": 0,
          "fg3a": 0,
          "fg3m": 0,
          "fga": 1,
          "fgm": 0,
          "fta": 0,
          "ftm": 0,
          "inTime": "12:00",
          "minutes": 5.9,
          "oreb": 1,
          "outTime": "6:07",
          "period": 2,
          "pf": 0,
          "plusMinus": 8,
          "pts": 0,
          "reb": 1,
          "stl": 0,
          "tov": 0
        },
        {
          "ast": 0,
          "blk": 0,
          "fg3a": 4,
          "fg3m": 2,
          "fga": 5,
          "fgm": 2,
          "fta": 0,
          "ftm": 0,
          "inTime": "9:41",
          "minutes": 9.7,
          "oreb": 5,
          "outTime": "0:00",
          "period": 4,
          "pf": 0,
          "plusMinus": -4,
          "pts": 6,
          "reb": 5,
          "stl": 0,
          "tov": 1
        }
      ],
      "team": "SAS",
      "totals": {
        "ast": 1,
        "blk": 0,
        "eff": 8,
        "fg3a": 4,
        "fg3m": 2,
        "fga": 6,
        "fgm": 2,
        "fta": 0,
        "ftm": 0,
        "hv": 6,
        "min": 15.6,
        "oreb": 3,
        "pf": 0,
        "plusMinus": 4,
        "prod": 0.77,
        "pts": 6,
        "reb": 6,
        "stl": 0,
        "tov": 1
      }
    },
    {
      "name": "Bismack Biyombo",
      "playerId": "202687",
      "position": "C",
      "starter": false,
      "stints": [
        {
          "ast": 1,
          "blk": 0,
          "fg3a": 0,
          "fg3m": 0,
          "fga": 0,
          "fgm": 0,
          "fta": 2,
          "ftm": 2,
          "inTime": "9:41",
          "minutes": 9.7,
          "oreb": 0,
          "outTime": "0:00",
          "period": 4,
          "pf": 2,
          "plusMinus": -4,
          "pts": 2,
          "reb": 1,
          "stl": 1,
          "tov": 0
        }
      ],
      "team": "SAS",
      "totals": {
        "ast": 1,
        "blk": 0,
        "eff": 5,
        "fg3a": 0,
        "fg3m": 0,
        "fga": 0,
        "fgm": 0,
        "fta": 2,
        "ftm": 2,
        "hv": 3,
        "min": 9.7,
        "oreb": 0,
        "pf": 2,
        "plusMinus": -4,
        "prod": 0.52,
        "pts": 2,
        "reb": 1,
        "stl": 1,
        "tov": 0
      }
    },
    {
      "name": "Jordan McLaughlin",
      "playerId": "1629162",
      "position": "G",
      "starter": false,
      "stints": [
        {
          "ast": 0,
          "blk": 1,
          "fg3a": 2,
          "fg3m": 0,
          "fga": 4,
          "fgm": 0,
          "fta": 0,
          "ftm": 0,
          "inTime": "9:41",
          "minutes": 9.7,
          "oreb": 0,
          "outTime": "0:00",
          "period": 4,
          "pf": 0,
          "plusMinus": -4,
          "pts": 0,
          "reb": 0,
          "stl": 0,
          "tov": 0
        }
      ],
      "team": "SAS",
      "totals": {
        "ast": 0,
        "blk": 1,
        "eff": -3,
        "fg3a": 2,
        "fg3m": 0,
        "fga": 4,
        "fgm": 0,
        "fta": 0,
        "ftm": 0,
        "hv": 1,
        "min": 9.7,
        "oreb": 0,
        "pf": 0,
        "plusMinus": -4,
        "prod": 0.1,
        "pts": 0,
        "reb": 0,
        "stl": 0,
        "tov": 0
      }
    },
    {
      "name": "Kelly Olynyk",
      "playerId": "203482",
      "position": "F-C",
      "starter": false,
      "stints": [
        {
          "ast": 1,
          "blk": 0,
          "fg3a": 0,
          "fg3m": 0,
          "fga": 0,
          "fgm": 0,
          "fta": 0,
          "ftm": 0,
          "inTime": "9:41",
          "minutes": 9.7,
          "oreb": 0,
          "outTime": "0:00",
          "period": 4,
          "pf": 0,
          "plusMinus": -4,
          "pts": 0,
          "reb": 3,
          "stl": 0,
          "tov": 1
        }
      ],
      "team": "SAS",
      "totals": {
        "ast": 1,
        "blk": 0,
        "eff": 3,
        "fg3a": 0,
        "fg3m": 0,
        "fga": 0,
        "fgm": 0,
        "fta": 0,
        "ftm": 0,
        "hv": 3,
        "min": 9.7,
        "oreb": 0,
        "pf": 0,
        "plusMinus": -4,
        "prod": 0.31,
        "pts": 0,
        "reb": 3,
        "stl": 0,
        "tov": 1
      }
    },
    {
      "name": "Jalen Green",
      "playerId": "1630224",
      "position": "G",
      "starter": true,
      "stints": [
        {
          "ast": 1,
          "blk": 0,
          "fg3a": 2,
          "fg3m": 1,
          "fga": 9,
          "fgm": 5,
          "fta": 0,
          "ftm": 0,
          "inTime": "12:00",
          "minutes": 9.1,
          "oreb": 0,
          "outTime": "2:53",
          "period": 1,
          "pf": 1,
          "plusMinus": -4,
          "pts": 11,
          "reb": 3,
          "stl": 2,
          "tov": 1
        },
        {
          "ast": 1,
          "blk": 0,
          "fg3a": 2,
          "fg3m": 1,
          "fga": 3,
          "fgm": 1,
          "fta": 0,
          "ftm": 0,
          "inTime": "9:32",
          "minutes": 4.8,
          "oreb": 0,
          "outTime": "4:46",
          "period": 2,
          "pf": 0,
          "plusMinus": -1,
          "pts": 3,
          "reb": 0,
          "stl": 0,
          "tov": 1
        },
        {
          "ast": 0,
          "blk": 0,
          "fg3a": 3,
          "fg3m": 1,
          "fga": 6,
          "fgm": 2,
          "fta": 0,
          "ftm": 0,
          "inTime": "12:00",
          "minutes": 7.8,
          "oreb": 0,
          "outTime": "4:09",
          "period": 3,
          "pf": 0,
          "plusMinus": -16,
          "pts": 5,
          "reb": 0,
          "stl": 0,
          "tov": 1
        },
        {
          "ast": 0,
          "blk": 0,
          "fg3a": 2,
          "fg3m": 1,
          "fga": 5,
          "fgm": 3,
          "fta": 0,
          "ftm": 0,
          "inTime": "12:00",
          "minutes": 4.4,
          "oreb": 0,
          "outTime": "7:34",
          "period": 4,
          "pf": 0,
          "plusMinus": 1,
          "pts": 7,
          "reb": 0,
          "stl": 1,
          "tov": 0
        }
      ],
      "team": "PHX",
      "totals": {
        "ast": 2,
        "blk": 0,
        "eff": 19,
        "fg3a": 9,
        "fg3m": 4,
        "fga": 23,
        "fgm": 11,
        "fta": 0,
        "ftm": 0,
        "hv": 5,
        "min": 26.2,
        "oreb": 0,
        "pf": 1,
        "plusMinus": -20,
        "prod": 1.18,
        "pts": 26,
        "reb": 3,
        "stl": 3,
        "tov": 3
      }
    },
    {
      "name": "Royce O'Neale",
      "playerId": "1626220",
      "position": "F",
      "starter": true,
      "stints": [
        {
          "ast": 0,
          "blk": 0,
          "fg3a": 0,
          "fg3m": 0,
          "fga": 1,
          "fgm": 0,
          "fta": 0,
          "ftm": 0,
          "inTime": "12:00",
          "minutes": 9.1,
          "oreb": 0,
          "outTime": "2:53",
          "period": 1,
          "pf": 0,
          "plusMinus": -4,
          "pts": 0,
          "reb": 1,
          "stl": 0,
          "tov": 0
        },
        {
          "ast": 1,
          "blk": 1,
          "fg3a": 3,
          "fg3m": 2,
          "fga": 4,
          "fgm": 3,
          "fta": 0,
          "ftm": 0,
          "inTime": "9:32",
          "minutes": 9.5,
          "oreb": 4,
          "outTime": "0:00",
          "period": 2,
          "pf": 2,
          "plusMinus": 2,
          "pts": 8,
          "reb": 5,
          "stl": 0,
          "tov": 0
        },
        {
          "ast": 0,
          "blk": 0,
          "fg3a": 2,
          "fg3m": 0,
          "fga": 3,
          "fgm": 0,
          "fta": 0,
          "ftm": 0,
          "inTime": "12:00",
          "minutes": 7.8,
          "oreb": 1,
          "outTime": "4:09",
          "period": 3,
          "pf": 0,
          "plusMinus": -4,
          "pts": 0,
          "reb": 1,
          "stl": 0,
          "tov": 0
        }
      ],
      "team": "PHX",
      "totals": {
        "ast": 1,
        "blk": 1,
        "eff": 12,
        "fg3a": 5,
        "fg3m": 2,
        "fga": 8,
        "fgm": 3,
        "fta": 0,
        "ftm": 0,
        "hv": 9,
        "min": 26.5,
        "oreb": 3,
        "pf": 2,
        "plusMinus": -18,
        "prod": 0.64,
        "pts": 8,
        "reb": 7,
        "stl": 0,
        "tov": 0
      }
    },
    {
      "name": "Mark Williams",
      "playerId": "1631109",
      "position": "C",
      "starter": true,
      "stints": [
        {
          "ast": 0,
          "blk": 1,
          "fg3a": 0,
          "fg3m": 0,
          "fga": 5,
          "fgm": 2,
          "fta": 0,
          "ftm": 0,
          "inTime": "12:00",
          "minutes": 9.1,
          "oreb": 2,
          "outTime": "2:53",
          "period": 1,
          "pf": 1,
          "plusMinus": -4,
          "pts": 4,
          "reb": 3,
          "stl": 0,
          "tov": 0
        },
        {
          "ast": 0,
          "blk": 0,
          "fg3a": 0,
          "fg3m": 0,
          "fga": 4,
          "fgm": 1,
          "fta": 0,
          "ftm": 0,
          "inTime": "10:31",
          "minutes": 5.8,
          "oreb": 5,
          "outTime": "4:46",
          "period": 2,
          "pf": 0,
          "plusMinus": -4,
          "pts": 2,
          "reb": 5,
          "stl": 0,
          "tov": 0
        },
        {
          "ast": 0,
          "blk": 0,
          "fg3a": 0,
          "fg3m": 0,
          "fga": 0,
          "fgm": 0,
          "fta": 0,
          "ftm": 0,
          "inTime": "1:15",
          "minutes": 1.2,
          "oreb": 0,
          "outTime": "0:00",
          "period": 2,
          "pf": 0,
          "plusMinus": 2,
          "pts": 0,
          "reb": 0,
          "stl": 0,
          "tov": 0
        },
        {
          "ast": 0,
          "blk": 0,
          "fg3a": 0,
          "fg3m": 0,
          "fga": 3,
          "fgm": 1,
          "fta": 4,
          "ftm": 3,
          "inTime": "12:00",
          "minutes": 6.6,
          "oreb": 2,
          "outTime": "5:23",
          "period": 3,
          "pf": 0,
          "plusMinus": -4,
          "pts": 5,
          "reb": 2,
          "stl": 0,
          "tov": 0
        }
      ],
      "team": "PHX",
      "totals": {
        "ast": 0,
        "blk": 1,
        "eff": 13,
        "fg3a": 0,
        "fg3m": 0,
        "fga": 12,
        "fgm": 4,
        "fta": 4,
        "ftm": 3,
        "hv": 11,
        "min": 22.7,
        "oreb": 4,
        "pf": 1,
        "plusMinus": -19,
        "prod": 0.97,
        "pts": 11,
        "reb": 10,
        "stl": 0,
        "tov": 0
      }
    },
    {
      "name": "Devin Booker",
      "playerId": "1626164",
      "position": "G",
      "starter": true,
      "stints": [
        {
          "ast": 0,
          "blk": 0,
          "fg3a": 1,
          "fg3m": 0,
          "fga": 5,
          "fgm": 2,
          "fta": 2,
          "ftm": 1,
          "inTime": "12:00",
          "minutes": 6.6,
          "oreb": 0,
          "outTime": "5:24",
          "period": 1,
          "pf": 1,
          "plusMinus": -3,
          "pts": 5,
          "reb": 1,
          "stl": 0,
          "tov": 0
        },
        {
          "ast": 0,
          "blk": 0,
          "fg3a": 1,
          "fg3m": 0,
          "fga": 1,
          "fgm": 0,
          "fta": 0,
          "ftm": 0,
          "inTime": "4:46",
          "minutes": 2.2,
          "oreb": 0,
          "outTime": "2:35",
          "period": 2,
          "pf": 0,
          "plusMinus": -4,
          "pts": 0,
          "reb": 0,
          "stl": 0,
          "tov": 1
        }
      ],
      "team": "PHX",
      "totals": {
        "ast": 0,
        "blk": 0,
        "eff": 0,
        "fg3a": 2,
        "fg3m": 0,
        "fga": 6,
        "fgm": 2,
        "fta": 2,
        "ftm": 1,
        "hv": 0,
        "min": 8.8,
        "oreb": 0,
        "pf": 1,
        "plusMinus": -7,
        "prod": 0.57,
        "pts": 5,
        "reb": 1,
        "stl": 0,
        "tov": 1
      }
    },
    {
      "name": "Collin Gillespie",
      "playerId": "1631221",
      "position": "G",
      "starter": true,
      "stints": [
        {
          "ast": 2,
          "blk": 0,
          "fg3a": 1,
          "fg3m": 0,
          "fga": 1,
          "fgm": 0,
          "fta": 0,
          "ftm": 0,
          "inTime": "12:00",
          "minutes": 5.0,
          "oreb": 0,
          "outTime": "7:00",
          "period": 1,
          "pf": 0,
          "plusMinus": 1,
          "pts": 0,
          "reb": 0,
          "stl": 0,
          "tov": 0
        },
        {
          "ast": 1,
          "blk": 0,
          "fg3a": 2,
          "fg3m": 1,
          "fga": 2,
          "fgm": 1,
          "fta": 0,
          "ftm": 0,
          "inTime": "5:24",
          "minutes": 5.4,
          "oreb": 0,
          "outTime": "0:00",
          "period": 1,
          "pf": 0,
          "plusMinus": -2,
          "pts": 3,
          "reb": 0,
          "stl": 0,
          "tov": 0
        },
        {
          "ast": 0,
          "blk": 0,
          "fg3a": 1,
          "fg3m": 0,
          "fga": 1,
          "fgm": 0,
          "fta": 0,
          "ftm": 0,
          "inTime": "12:00",
          "minutes": 2.5,
          "oreb": 0,
          "outTime": "9:32",
          "period": 2,
          "pf": 1,
          "plusMinus": -6,
          "pts": 0,
          "reb": 0,
          "stl": 0,
          "tov": 1
        },
        {
          "ast": 1,
          "blk": 0,
          "fg3a": 2,
          "fg3m": 1,
          "fga": 3,
          "fgm": 1,
          "fta": 0,
          "ftm": 0,
          "inTime": "3:35",
          "minutes": 3.6,
          "oreb": 0,
          "outTime": "0:00",
          "period": 2,
          "pf": 1,
          "plusMinus": 5,
          "pts": 3,
          "reb": 0,
          "stl": 0,
          "tov": 0
        },
        {
          "ast": 1,
          "blk": 0,
          "fg3a": 1,
          "fg3m": 0,
          "fga": 2,
          "fgm": 0,
          "fta": 0,
          "ftm": 0,
          "inTime": "12:00",
          "minutes": 4.7,
          "oreb": 0,
          "outTime": "7:19",
          "period": 3,
          "pf": 0,
          "plusMinus": -4,
          "pts": 0,
          "reb": 0,
          "stl": 1,
          "tov": 0
        },
        {
          "ast": 1,
          "blk": 0,
          "fg3a": 1,
          "fg3m": 0,
          "fga": 4,
          "fgm": 1,
          "fta": 0,
          "ftm": 0,
          "inTime": "4:09",
          "minutes": 4.2,
          "oreb": 0,
          "outTime": "0:00",
          "period": 3,
          "pf": 1,
          "plusMinus": 1,
          "pts": 2,
          "reb": 0,
          "stl": 0,
          "tov": 0
        },
        {
          "ast": 2,
          "blk": 0,
          "fg3a": 0,
          "fg3m": 0,
          "fga": 0,
          "fgm": 0,
          "fta": 0,
          "ftm": 0,
          "inTime": "12:00",
          "minutes": 4.4,
          "oreb": 1,
          "outTime": "7:34",
          "period": 4,
          "pf": 0,
          "plusMinus": -3,
          "pts": 0,
          "reb": 2,
          "stl": 0,
          "tov": 0
        }
      ],
      "team": "PHX",
      "totals": {
        "ast": 8,
        "blk": 0,
        "eff": 8,
        "fg3a": 8,
        "fg3m": 2,
        "fga": 13,
        "fgm": 3,
        "fta": 0,
        "ftm": 0,
        "hv": 10,
        "min": 29.7,
        "oreb": 1,
        "pf": 3,
        "plusMinus": -11,
        "prod": 0.61,
        "pts": 8,
        "reb": 2,
        "stl": 1,
        "tov": 1
      }
    },
    {
      "name": "Jordan Goodwin",
      "playerId": "1630692",
      "position": "G",
      "starter": false,
      "stints": [
        {
          "ast": 0,
          "blk": 0,
          "fg3a": 3,
          "fg3m": 0,
          "fga": 3,
          "fgm": 0,
          "fta": 0,
          "ftm": 0,
          "inTime": "7:00",
          "minutes": 7.0,
          "oreb": 0,
          "outTime": "0:00",
          "period": 1,
          "pf": 0,
          "plusMinus": -5,
          "pts": 0,
          "reb": 2,
          "stl": 0,
          "tov": 0
        },
        {
          "ast": 0,
          "blk": 0,
          "fg3a": 0,
          "fg3m": 0,
          "fga": 0,
          "fgm": 0,
          "fta": 0,
          "ftm": 0,
          "inTime": "12:00",
          "minutes": 2.1,
          "oreb": 0,
          "outTime": "9:53",
          "period": 2,
          "pf": 0,
          "plusMinus": -6,
          "pts": 0,
          "reb": 0,
          "stl": 0,
          "tov": 0
        },
        {
          "ast": 1,
          "blk": 0,
          "fg3a": 2,
          "fg3m": 2,
          "fga": 2,
          "fgm": 2,
          "fta": 0,
          "ftm": 0,
          "inTime": "4:46",
          "minutes": 4.8,
          "oreb": 0,
          "outTime": "0:00",
          "period": 2,
          "pf": 0,
          "plusMinus": 3,
          "pts": 6,
          "reb": 0,
          "stl": 0,
          "tov": 0
        },
        {
          "ast": 0,
          "blk": 0,
          "fg3a": 0,
          "fg3m": 0,
          "fga": 4,
          "fgm": 2,
          "fta": 0,
          "ftm": 0,
          "inTime": "12:00",
          "minutes": 9.7,
          "oreb": 2,
          "outTime": "2:16",
          "period": 3,
          "pf": 0,
          "plusMinus": -4,
          "pts": 4,
          "reb": 2,
          "stl": 0,
          "tov": 0
        },
        {
          "ast": 0,
          "blk": 0,
          "fg3a": 2,
          "fg3m": 0,
          "fga": 3,
          "fgm": 0,
          "fta": 0,
          "ftm": 0,
          "inTime": "7:34",
          "minutes": 3.6,
          "oreb": 0,
          "outTime": "3:55",
          "period": 4,
          "pf": 1,
          "plusMinus": -4,
          "pts": 0,
          "reb": 0,
          "stl": 0,
          "tov": 0
        }
      ],
      "team": "PHX",
      "totals": {
        "ast": 1,
        "blk": 0,
        "eff": 7,
        "fg3a": 7,
        "fg3m": 2,
        "fga": 12,
        "fgm": 4,
        "fta": 0,
        "ftm": 0,
        "hv": 5,
        "min": 27.3,
        "oreb": 1,
        "pf": 1,
        "plusMinus": -27,
        "prod": 0.55,
        "pts": 10,
        "reb": 4,
        "stl": 0,
        "tov": 0
      }
    },
    {
      "name": "Ryan Dunn",
      "playerId": "1642346",
      "position": "F",
      "starter": false,
      "stints": [
        {
          "ast": 0,
          "blk": 0,
          "fg3a": 0,
          "fg3m": 0,
          "fga": 0,
          "fgm": 0,
          "fta": 0,
          "ftm": 0,
          "inTime": "2:53",
          "minutes": 2.9,
          "oreb": 0,
          "outTime": "0:00",
          "period": 1,
          "pf": 1,
          "plusMinus": -1,
          "pts": 0,
          "reb": 1,
          "stl": 0,
          "tov": 0
        },
        {
          "ast": 0,
          "blk": 1,
          "fg3a": 0,
          "fg3m": 0,
          "fga": 0,
          "fgm": 0,
          "fta": 0,
          "ftm": 0,
          "inTime": "12:00",
          "minutes": 2.5,
          "oreb": 1,
          "outTime": "9:32",
          "period": 2,
          "pf": 0,
          "plusMinus": -6,
          "pts": 0,
          "reb": 1,
          "stl": 0,
          "tov": 0
        },
        {
          "ast": 1,
          "blk": 0,
          "fg3a": 1,
          "fg3m": 0,
          "fga": 1,
          "fgm": 0,
          "fta": 0,
          "ftm": 0,
          "inTime": "4:09",
          "minutes": 4.2,
          "oreb": 1,
          "outTime": "0:00",
          "period": 3,
          "pf": 1,
          "plusMinus": 1,
          "pts": 0,
          "reb": 1,
          "stl": 0,
          "tov": 0
        },
        {
          "ast": 0,
          "blk": 1,
          "fg3a": 1,
          "fg3m": 0,
          "fga": 3,
          "fgm": 1,
          "fta": 0,
          "ftm": 0,
          "inTime": "12:00",
          "minutes": 12.0,
          "oreb": 1,
          "outTime": "0:00",
          "period": 4,
          "pf": 0,
          "plusMinus": 0,
          "pts": 2,
          "reb": 1,
          "stl": 0,
          "tov": 0
        }
      ],
      "team": "PHX",
      "totals": {
        "ast": 1,
        "blk": 2,
        "eff": 6,
        "fg3a": 2,
        "fg3m": 0,
        "fga": 4,
        "fgm": 1,
        "fta": 0,
        "ftm": 0,
        "hv": 7,
        "min": 21.5,
        "oreb": 2,
        "pf": 2,
        "plusMinus": -9,
        "prod": 0.42,
        "pts": 2,
        "reb": 4,
        "stl": 0,
        "tov": 0
      }
    },
    {
      "name": "Amir Coffey",
      "playerId": "1629599",
      "position": "G-F",
      "starter": false,
      "stints": [
        {
          "ast": 0,
          "blk": 0,
          "fg3a": 0,
          "fg3m": 0,
          "fga": 0,
          "fgm": 0,
          "fta": 0,
          "ftm": 0,
          "inTime": "2:53",
          "minutes": 2.9,
          "oreb": 0,
          "outTime": "0:00",
          "period": 1,
          "pf": 0,
          "plusMinus": -1,
          "pts": 0,
          "reb": 0,
          "stl": 0,
          "tov": 0
        },
        {
          "ast": 0,
          "blk": 0,
          "fg3a": 1,
          "fg3m": 0,
          "fga": 1,
          "fgm": 0,
          "fta": 0,
          "ftm": 0,
          "inTime": "12:00",
          "minutes": 5.0,
          "oreb": 0,
          "outTime": "6:57",
          "period": 2,
          "pf": 0,
          "plusMinus": -6,
          "pts": 0,
          "reb": 0,
          "stl": 0,
          "tov": 0
        },
        {
          "ast": 1,
          "blk": 0,
          "fg3a": 0,
          "fg3m": 0,
          "fga": 0,
          "fgm": 0,
          "fta": 0,
          "ftm": 0,
          "inTime": "3:55",
          "minutes": 3.9,
          "oreb": 0,
          "outTime": "0:00",
          "period": 4,
          "pf": 1,
          "plusMinus": 3,
          "pts": 0,
          "reb": 0,
          "stl": 0,
          "tov": 0
        }
      ],
      "team": "PHX",
      "totals": {
        "ast": 1,
        "blk": 0,
        "eff": 0,
        "fg3a": 1,
        "fg3m": 0,
        "fga": 1,
        "fgm": 0,
        "fta": 0,
        "ftm": 0,
        "hv": 1,
        "min": 11.8,
        "oreb": 0,
        "pf": 1,
        "plusMinus": -7,
        "prod": 0.08,
        "pts": 0,
        "reb": 0,
        "stl": 0,
        "tov": 0
      }
    },
    {
      "name": "Oso Ighodaro",
      "playerId": "1642345",
      "position": "F",
      "starter": false,
      "stints": [
        {
          "ast": 1,
          "blk": 0,
          "fg3a": 0,
          "fg3m": 0,
          "fga": 1,
          "fgm": 1,
          "fta": 0,
          "ftm": 0,
          "inTime": "2:53",
          "minutes": 2.9,
          "oreb": 0,
          "outTime": "0:00",
          "period": 1,
          "pf": 0,
          "plusMinus": -1,
          "pts": 2,
          "reb": 0,
          "stl": 0,
          "tov": 0
        },
        {
          "ast": 0,
          "blk": 0,
          "fg3a": 0,
          "fg3m": 0,
          "fga": 1,
          "fgm": 0,
          "fta": 0,
          "ftm": 0,
          "inTime": "12:00",
          "minutes": 1.5,
          "oreb": 0,
          "outTime": "10:31",
          "period": 2,
          "pf": 0,
          "plusMinus": -6,
          "pts": 0,
          "reb": 0,
          "stl": 0,
          "tov": 0
        },
        {
          "ast": 2,
          "blk": 0,
          "fg3a": 0,
          "fg3m": 0,
          "fga": 2,
          "fgm": 1,
          "fta": 0,
          "ftm": 0,
          "inTime": "4:46",
          "minutes": 3.5,
          "oreb": 0,
          "outTime": "1:15",
          "period": 2,
          "pf": 2,
          "plusMinus": -1,
          "pts": 2,
          "reb": 0,
          "stl": 0,
          "tov": 1
        },
        {
          "ast": 1,
          "blk": 0,
          "fg3a": 0,
          "fg3m": 0,
          "fga": 3,
          "fgm": 2,
          "fta": 0,
          "ftm": 0,
          "inTime": "5:23",
          "minutes": 5.4,
          "oreb": 0,
          "outTime": "0:00",
          "period": 3,
          "pf": 0,
          "plusMinus": -2,
          "pts": 4,
          "reb": 2,
          "stl": 0,
          "tov": 0
        },
        {
          "ast": 1,
          "blk": 0,
          "fg3a": 0,
          "fg3m": 0,
          "fga": 1,
          "fgm": 1,
          "fta": 0,
          "ftm": 0,
          "inTime": "12:00",
          "minutes": 4.4,
          "oreb": 0,
          "outTime": "7:34",
          "period": 4,
          "pf": 0,
          "plusMinus": -3,
          "pts": 2,
          "reb": 0,
          "stl": 1,
          "tov": 0
        }
      ],
      "team": "PHX",
      "totals": {
        "ast": 5,
        "blk": 0,
        "eff": 14,
        "fg3a": 0,
        "fg3m": 0,
        "fga": 8,
        "fgm": 5,
        "fta": 0,
        "ftm": 0,
        "hv": 7,
        "min": 17.7,
        "oreb": 0,
        "pf": 2,
        "plusMinus": -7,
        "prod": 0.96,
        "pts": 10,
        "reb": 2,
        "stl": 1,
        "tov": 1
      }
    },
    {
      "name": "Isaiah Livers",
      "playerId": "1630587",
      "position": "F",
      "starter": false,
      "stints": [
        {
          "ast": 0,
          "blk": 0,
          "fg3a": 1,
          "fg3m": 0,
          "fga": 1,
          "fgm": 0,
          "fta": 0,
          "ftm": 0,
          "inTime": "9:53",
          "minutes": 5.1,
          "oreb": 1,
          "outTime": "4:46",
          "period": 2,
          "pf": 0,
          "plusMinus": -4,
          "pts": 0,
          "reb": 1,
          "stl": 0,
          "tov": 0
        },
        {
          "ast": 1,
          "blk": 0,
          "fg3a": 0,
          "fg3m": 0,
          "fga": 0,
          "fgm": 0,
          "fta": 0,
          "ftm": 0,
          "inTime": "2:35",
          "minutes": 2.6,
          "oreb": 0,
          "outTime": "0:00",
          "period": 2,
          "pf": 0,
          "plusMinus": 7,
          "pts": 0,
          "reb": 0,
          "stl": 0,
          "tov": 0
        },
        {
          "ast": 0,
          "blk": 0,
          "fg3a": 0,
          "fg3m": 0,
          "fga": 0,
          "fgm": 0,
          "fta": 0,
          "ftm": 0,
          "inTime": "2:16",
          "minutes": 2.3,
          "oreb": 0,
          "outTime": "0:00",
          "period": 3,
          "pf": 0,
          "plusMinus": -1,
          "pts": 0,
          "reb": 0,
          "stl": 0,
          "tov": 0
        }
      ],
      "team": "PHX",
      "totals": {
        "ast": 1,
        "blk": 0,
        "eff": 1,
        "fg3a": 1,
        "fg3m": 0,
        "fga": 1,
        "fgm": 0,
        "fta": 0,
        "ftm": 0,
        "hv": 2,
        "min": 10.0,
        "oreb": 1,
        "pf": 0,
        "plusMinus": 2,
        "prod": 0.2,
        "pts": 0,
        "reb": 1,
        "stl": 0,
        "tov": 0
      }
    },
    {
      "name": "Jamaree Bouyea",
      "playerId": "1631123",
      "position": "G",
      "starter": false,
      "stints": [
        {
          "ast": 0,
          "blk": 0,
          "fg3a": 0,
          "fg3m": 0,
          "fga": 0,
          "fgm": 0,
          "fta": 0,
          "ftm": 0,
          "inTime": "6:57",
          "minutes": 3.4,
          "oreb": 0,
          "outTime": "3:35",
          "period": 2,
          "pf": 0,
          "plusMinus": -3,
          "pts": 0,
          "reb": 0,
          "stl": 0,
          "tov": 0
        },
        {
          "ast": 0,
          "blk": 1,
          "fg3a": 0,
          "fg3m": 0,
          "fga": 2,
          "fgm": 1,
          "fta": 0,
          "ftm": 0,
          "inTime": "7:19",
          "minutes": 7.3,
          "oreb": 1,
          "outTime": "0:00",
          "period": 3,
          "pf": 1,
          "plusMinus": -7,
          "pts": 2,
          "reb": 2,
          "stl": 1,
          "tov": 2
        },
        {
          "ast": 2,
          "blk": 0,
          "fg3a": 3,
          "fg3m": 1,
          "fga": 5,
          "fgm": 2,
          "fta": 0,
          "ftm": 0,
          "inTime": "7:34",
          "minutes": 7.6,
          "oreb": 1,
          "outTime": "0:00",
          "period": 4,
          "pf": 0,
          "plusMinus": -1,
          "pts": 5,
          "reb": 1,
          "stl": 0,
          "tov": 0
        }
      ],
      "team": "PHX",
      "totals": {
        "ast": 2,
        "blk": 1,
        "eff": 8,
        "fg3a": 3,
        "fg3m": 1,
        "fga": 7,
        "fgm": 3,
        "fta": 0,
        "ftm": 0,
        "hv": 5,
        "min": 18.2,
        "oreb": 1,
        "pf": 1,
        "plusMinus": -11,
        "prod": 0.66,
        "pts": 7,
        "reb": 3,
        "stl": 1,
        "tov": 2
      }
    },
    {
      "name": "Rasheer Fleming",
      "playerId": "1642853",
      "position": "F",
      "starter": false,
      "stints": [
        {
          "ast": 0,
          "blk": 0,
          "fg3a": 2,
          "fg3m": 1,
          "fga": 4,
          "fgm": 1,
          "fta": 0,
          "ftm": 0,
          "inTime": "12:00",
          "minutes": 12.0,
          "oreb": 2,
          "outTime": "0:00",
          "period": 4,
          "pf": 0,
          "plusMinus": 0,
          "pts": 3,
          "reb": 3,
          "stl": 0,
          "tov": 1
        }
      ],
      "team": "PHX",
      "totals": {
        "ast": 0,
        "blk": 0,
        "eff": 2,
        "fg3a": 2,
        "fg3m": 1,
        "fga": 4,
        "fgm": 1,
        "fta": 0,
        "ftm": 0,
        "hv": 2,
        "min": 12.0,
        "oreb": 2,
        "pf": 0,
        "plusMinus": 0,
        "prod": 0.42,
        "pts": 3,
        "reb": 3,
        "stl": 0,
        "tov": 1
      }
    },
    {
      "name": "Khaman Maluach",
      "playerId": "1642863",
      "position": "C",
      "starter": false,
      "stints": [
        {
          "ast": 0,
          "blk": 0,
          "fg3a": 2,
          "fg3m": 0,
          "fga": 6,
          "fgm": 2,
          "fta": 0,
          "ftm": 0,
          "inTime": "7:34",
          "minutes": 7.6,
          "oreb": 5,
          "outTime": "0:00",
          "period": 4,
          "pf": 1,
          "plusMinus": -1,
          "pts": 4,
          "reb": 6,
          "stl": 1,
          "tov": 2
        }
      ],
      "team": "PHX",
      "totals": {
        "ast": 0,
        "blk": 0,
        "eff": 5,
        "fg3a": 2,
        "fg3m": 0,
        "fga": 6,
        "fgm": 2,
        "fta": 0,
        "ftm": 0,
        "hv": 5,
        "min": 7.6,
        "oreb": 4,
        "pf": 1,
        "plusMinus": -1,
        "prod": 1.18,
        "pts": 4,
        "reb": 6,
        "stl": 1,
        "tov": 2
      }
    }
  ],
  "teamTotals": {
    "away": {
      "ast": 22,
      "blk": 5,
      "fg3a": 42,
      "fg3m": 12,
      "fga": 105,
      "fgm": 39,
      "fta": 6,
      "ftm": 4,
      "oreb": 19,
      "pf": 16,
      "pts": 94,
      "reb": 46,
      "stl": 7,
      "tov": 11
    },
    "home": {
      "ast": 30,
      "blk": 7,
      "fg3a": 37,
      "fg3m": 13,
      "fga": 87,
      "fgm": 45,
      "fta": 20,
      "ftm": 18,
      "oreb": 11,
      "pf": 12,
      "pts": 121,
      "reb": 50,
      "stl": 6,
      "tov": 11
    }
  }
}